lunchtime/__init__.py
lunchtime/cli.py
lunchtime/functions.py
lunchtime/lunchtime.py
lunchtime-0.2.0.dist-info/AUTHORS.rst
lunchtime-0.2.0.dist-info/LICENSE
lunchtime-0.2.0.dist-info/METADATA
lunchtime-0.2.0.dist-info/WHEEL
lunchtime-0.2.0.dist-info/entry_points.txt
lunchtime-0.2.0.dist-info/top_level.txt
lunchtime-0.2.0.dist-info/RECORD
