Metadata-Version: 2.1
Name: lunchtime
Version: 0.2.0
Summary: Ignore all terminal commands while it's lunchtime!
Home-page: https://github.com/robertopreste/lunchtime
Author: Roberto Preste
Author-email: robertopreste@gmail.com
License: MIT license
Keywords: lunchtime
Platform: UNKNOWN
Classifier: Development Status :: 2 - Pre-Alpha
Classifier: Intended Audience :: Developers
Classifier: License :: OSI Approved :: MIT License
Classifier: Natural Language :: English
Classifier: Programming Language :: Python :: 3
Classifier: Programming Language :: Python :: 3.5
Classifier: Programming Language :: Python :: 3.6
Classifier: Programming Language :: Python :: 3.7
Requires-Dist: Click (>=7.0)
